Metadata-Version: 2.1
Name: Mojo2py
Version: 1.3
Summary: A python package which converts a mojo file (.mojo or .🔥) into a python file.
Home-page: https://github.com/venvis/mojo2py
Author: Vishal
Author-email: vishalvenkat2604@gmail.com
License: MIT
Keywords: conversion
Classifier: Development Status :: 3 - Alpha
Classifier: Intended Audience :: Developers
Classifier: License :: OSI Approved :: MIT License
Classifier: Programming Language :: Python :: 3
